<?xml version="1.0" standalone="yes" ?>
<?xml-stylesheet href="x2script.xsl" type="text/xsl" ?>
<script>
<name>setup.freight.drone.transfer</name>
<version>7</version>
<engineversion>42</engineversion>
<description>Setup for the freight drone transfer script</description>
<arguments>
</arguments>
<sourcetext>
<line linenr="001" indent=""><text>load&#160;text:&#160;id=</text><var>8222</var></line>
<line linenr="002" indent=""></line>
<line linenr="003" indent=""><text>set&#160;global&#160;variable:&#160;name=</text><var>'freight.drone.transfer.PageID'</var><text>&#160;value=</text><var>8222</var></line>
<line linenr="004" indent=""><text>set&#160;global&#160;variable:&#160;name=</text><var>'freight.drone.transfer.Version.Format'</var><text>&#160;value=</text><var>'v&#160;beta.%s'</var></line>
<line linenr="005" indent=""></line>
<line linenr="006" indent=""><text>set&#160;script&#160;command&#160;upgrade:&#160;command=</text><var>COMMAND_DRONE_WARE_EXCHANGE</var><text>&#160;&#160;upgrade=</text><var>Handelssoftware&#160;MK2</var></line>
<line linenr="007" indent=""><text>set&#160;script&#160;command&#160;upgrade:&#160;command=</text><var>COMMAND_DRONE_WARE_EXCHANGE</var><text>&#160;&#160;upgrade=</text><var>Frachtdrohne</var></line>
<line linenr="008" indent=""></line>
<line linenr="009" indent=""></line>
<line linenr="010" indent=""><text>global&#160;script&#160;map:&#160;set:&#160;key=</text><var>COMMAND_DRONE_WARE_EXCHANGE</var><text>,&#160;class=</text><var>Großschiff</var><text>,&#160;race=</text><var>Player</var><text>,&#160;script=</text><call>plugin.freight.drone.gui</call><text>,&#160;prio=</text><var>0</var></line>
<line linenr="011" indent=""><text>global&#160;script&#160;map:&#160;ignore:&#160;key=</text><var>COMMAND_DRONE_WARE_EXCHANGE</var><text>,&#160;class=</text><var>M8</var><text>,&#160;race=</text><var>Player</var></line>
<line linenr="012" indent=""></line>
<line linenr="013" indent=""><text>set&#160;ship&#160;command&#160;preload&#160;script:&#160;command=</text><var>COMMAND_DRONE_WARE_EXCHANGE</var><text>&#160;script=</text><call>plugin.freight.drone.gui</call></line>
<line linenr="014" indent=""></line>
<line linenr="015" indent=""><text>return&#160;</text><var>null</var></line>
</sourcetext>
<codearray>

<sval type="array" size="10">
  <sval type="string" val="setup.freight.drone.transfer"/>
  <sval type="int" val="42"/>
  <sval type="string" val="Setup for the freight drone transfer script"/>
  <sval type="int" val="7"/>
  <sval type="int" val="0"/>
  <sval type="int" val="0"/>
  <sval type="array" size="9">
    <sval type="array" size="3">
      <sval type="int" val="151"/>
      <sval type="int" val="4"/>
      <sval type="int" val="8222"/>
    </sval>
    <sval type="array" size="5">
      <sval type="int" val="157"/>
      <sval type="int" val="5"/>
      <sval type="string" val="freight.drone.transfer.PageID"/>
      <sval type="int" val="4"/>
      <sval type="int" val="8222"/>
    </sval>
    <sval type="array" size="5">
      <sval type="int" val="157"/>
      <sval type="int" val="5"/>
      <sval type="string" val="freight.drone.transfer.Version.Format"/>
      <sval type="int" val="5"/>
      <sval type="string" val="v beta.%s"/>
    </sval>
    <sval type="array" size="5">
      <sval type="int" val="144"/>
      <sval type="int" val="18"/>
      <sval type="int" val="422"/>
      <sval type="int" val="9"/>
      <sval type="int" val="1048631"/>
    </sval>
    <sval type="array" size="5">
      <sval type="int" val="144"/>
      <sval type="int" val="18"/>
      <sval type="int" val="422"/>
      <sval type="int" val="9"/>
      <sval type="int" val="1048656"/>
    </sval>
    <sval type="array" size="10">
      <sval type="int" val="118"/>
      <sval type="int" val="18"/>
      <sval type="int" val="422"/>
      <sval type="string" val="plugin.freight.drone.gui"/>
      <sval type="int" val="4"/>
      <sval type="int" val="0"/>
      <sval type="int" val="12"/>
      <sval type="int" val="2073"/>
      <sval type="int" val="10"/>
      <sval type="int" val="10"/>
    </sval>
    <sval type="array" size="7">
      <sval type="int" val="127"/>
      <sval type="int" val="18"/>
      <sval type="int" val="422"/>
      <sval type="int" val="12"/>
      <sval type="int" val="2142"/>
      <sval type="int" val="10"/>
      <sval type="int" val="10"/>
    </sval>
    <sval type="array" size="4">
      <sval type="int" val="1466"/>
      <sval type="int" val="18"/>
      <sval type="int" val="422"/>
      <sval type="string" val="plugin.freight.drone.gui"/>
    </sval>
    <sval type="array" size="3">
      <sval type="int" val="103"/>
      <sval type="int" val="0"/>
      <sval type="int" val="0"/>
    </sval>
  </sval>
  <sval type="int" val="0"/>
  <sval type="array" size="6">
    <sval type="array" size="2">
      <sval type="int" val="1"/>
      <sval type="int" val="2"/>
    </sval>
    <sval type="array" size="2">
      <sval type="int" val="3"/>
      <sval type="int" val="2"/>
    </sval>
    <sval type="array" size="2">
      <sval type="int" val="5"/>
      <sval type="int" val="2"/>
    </sval>
    <sval type="array" size="2">
      <sval type="int" val="5"/>
      <sval type="int" val="2"/>
    </sval>
    <sval type="array" size="2">
      <sval type="int" val="7"/>
      <sval type="int" val="2"/>
    </sval>
    <sval type="array" size="2">
      <sval type="int" val="8"/>
      <sval type="int" val="2"/>
    </sval>
  </sval>
  <sval type="int" val="0"/>
</sval>

</codearray>
</script>
